{
    "ingredients": [
        "2 Archer Farms\u2122 organic spinach & garlic with feta chicken sausages, crumbled",
        "2 cups Archer Farms\u2122 organic tomato basil pasta sauce",
        "1 tablespoon Archer farms\u2122 organic extra virgin olive oil",
        "1 (18 ounce) package organic polenta",
        "1 tablespoon chopped organic parsley"
    ],
    "instructions": [
        "Heat sausage and sauce in small saucepan over low heat until hot.",
        "Meanwhile, cut polenta into 12 slices.",
        "In 12-inch skillet heat olive oil over medium heat until hot.",
        "Add polenta slices.",
        "Cook 6 to 7 minutes or until light golden brown, turning once.",
        "To serve, place 3 slices on serving plate, top with 1/4 of the sausage mixture.",
        "Sprinkle with parsley.",
        "Serve immediately."
    ],
    "title": "Chicken Sausage Marinara over Polenta",
    "photo_url": "http://images.media-allrecipes.com/global/recipes/nophoto/nopicture-910x511.png",
    "url": "http://allrecipes.com/Recipe/156559/",
    "normalized_ingredients": {
        "I_0EQGCSB": "Archer Farms\u2122 organic spinach & garlic with feta chicken sausages",
        "I39jMOuBo": "Archer Farms\u2122 organic tomato basil pasta sauce",
        "IpLlyIme6": "Archer farms\u2122 organic extra virgin olive oil",
        "IUyl8-qqG": "organic polenta",
        "IE0aARl7-": "organic parsley"
    },
    "status": 0,
    "steps": [
        "Heat sausage and sauce in small saucepan over low heat until hot.",
        "Meanwhile, cut polenta into 12 slices. In 12-inch skillet heat olive oil over medium heat until hot. Add polenta slices. Cook 6 to 7 minutes or until light golden brown, turning once.",
        "To serve, place 3 slices on serving plate, top with 1/4 of the sausage mixture. Sprinkle with parsley. Serve immediately."
    ],
    "labels": [
        [],
        [],
        [],
        [],
        [],
        [],
        [],
        []
    ]
}