{
    "ingredients": [
        "6 cups Crispix* Krispies* cereal",
        "1 cup mixed nuts or peanuts",
        "1 cup pretzels",
        "2 tablespoons butter or margarine, melted",
        "1/4 teaspoon garlic salt",
        "1/4 teaspoon onion salt",
        "2 teaspoons lemon juice",
        "1 tablespoon Worcestershire sauce"
    ],
    "instructions": [
        "Combine cereal, nuts and pretzels in 3.5 L (13 x 9\") baking pan or roasting pan. Set aside",
        "Stir together remaining ingredients. Drizzle over cereal mixture, gently tossing until evenly coated.",
        "Bake at 120 degrees C (250 degrees F) 45 minutes, stirring every 15 minutes. Cool. Store in airtight container."
    ],
    "title": "Crispix*  Krispies* Original Mix",
    "photo_url": "http://images.media-allrecipes.com/userphotos/250x250/981404.jpg",
    "url": "http://allrecipes.com/Recipe/216478/",
    "normalized_ingredients": {
        "IryBzNtlq": "Crispix* Krispies* cereal",
        "IT3cGmkdk": "mixed nuts or peanuts",
        "I45McRyOI": "pretzels",
        "IJiuoefFg": "butter or margarine",
        "IOHK_fJm8": "garlic salt",
        "IRHxv_GTR": "onion salt",
        "I5wmzk9dU": "lemon juice",
        "Ih0sQOBSE": "Worcestershire sauce"
    },
    "status": 0,
    "sentences": [
        "Combine cereal, nuts and pretzels in 3.5 L (13 x 9\") baking pan or roasting pan.",
        "Set aside",
        "Stir together remaining ingredients.",
        "Drizzle over cereal mixture, gently tossing until evenly coated.",
        "Bake at 120 degrees C",
        "(250 degrees F)",
        "45 minutes, stirring every 15 minutes.",
        "Cool.",
        "Store in airtight container."
    ],
    "labels": [
        [],
        [],
        []
    ],
    "sentence_labels": [
        [],
        [],
        [],
        [],
        [],
        [],
        [],
        [],
        []
    ]
}