{
    "ingredients": [
        "1 pound lean ground beef",
        "1 cup water",
        "1 (8 ounce) can tomato sauce",
        "1 (1.25 ounce) package chili seasoning mix",
        "1 tablespoon prepared yellow mustard",
        "1 teaspoon onion powder",
        "1/2 teaspoon garlic powder"
    ],
    "instructions": [
        "Stir lean ground beef, water, tomato sauce, chili seasoning mix, yellow mustard, onion powder, and garlic powder together in a large saucepan; bring to a boil, stirring often.",
        "Cover, reduce heat to low, and simmer until ground beef is no longer pink, about 10 minutes.",
        "Remove lid and simmer sauce until thickened, about 20 more minutes."
    ],
    "title": "Chili Style Coney Sauce",
    "photo_url": "http://images.media-allrecipes.com/userphotos/560x315/3584656.jpg",
    "url": "http://allrecipes.com/Recipe/230895/",
    "normalized_ingredients": {
        "443": "lean ground beef",
        "714": "water",
        "684": "tomato sauce",
        "173": "chili seasoning mix",
        "547": "prepared yellow mustard",
        "492": "onion powder",
        "360": "garlic powder"
    },
    "status": 0,
    "labels": [
        [],
        []
    ],
    "steps": [
        "Stir lean ground beef, water, tomato sauce, chili seasoning mix, yellow mustard, onion powder, and garlic powder together in a large saucepan; bring to a boil, stirring often. Cover, reduce heat to low, and simmer until ground beef is no longer pink, about 10 minutes.",
        "Remove lid and simmer sauce until thickened, about 20 more minutes."
    ]
}