{
    "ingredients": [
        "1/4 cup chopped onion",
        "5 tablespoons soy sauce",
        "2 1/2 tablespoons brown sugar",
        "2 tablespoons minced garlic",
        "2 tablespoons sesame oil",
        "1 tablespoon sesame seeds",
        "1/2 teaspoon cayenne",
        "salt and ground black pepper to taste",
        "1 pound skinless, boneless chicken breasts, cut into thin strips"
    ],
    "instructions": [
        "Whisk onion, soy sauce, brown sugar, garlic, sesame oil, sesame seeds, cayenne pepper, salt, and black pepper together in a bowl until marinade is smooth.",
        "Cook and stir chicken and marinade together in a large skillet over medium-high heat until chicken is cooked through, about 15 minutes."
    ],
    "title": "Skillet Chicken Bulgogi",
    "photo_url": "http://images.media-allrecipes.com/userphotos/560x315/2280937.jpg",
    "url": "http://allrecipes.com/Recipe/240400/",
    "normalized_ingredients": {
        "Iz0wiMjVJ": "onion",
        "ILAT-xDbX": "soy sauce",
        "IRG-HJdJz": "brown sugar",
        "IzPYYTv5e": "garlic",
        "IpyJf3OVq": "sesame oil",
        "IS0gcu44e": "sesame seeds",
        "I-5bomrDf": "cayenne",
        "IukXkN8DV": "salt and ground black pepper to taste",
        "I7RMBnD2u": "skinless, boneless chicken breasts"
    },
    "status": 0,
    "steps": [
        "Whisk onion, soy sauce, brown sugar, garlic, sesame oil, sesame seeds, cayenne pepper, salt, and black pepper together in a bowl until marinade is smooth.",
        "Cook and stir chicken and marinade together in a large skillet over medium-high heat until chicken is cooked through, about 15 minutes."
    ],
    "labels": [
        [],
        []
    ]
}